javautils/__init__.py
javautils/clone.py
javautils/main.py
javautils-0.1.0.dist-info/LICENSE
javautils-0.1.0.dist-info/METADATA
javautils-0.1.0.dist-info/WHEEL
javautils-0.1.0.dist-info/entry_points.txt
javautils-0.1.0.dist-info/top_level.txt
javautils-0.1.0.dist-info/RECORD
