Metadata-Version: 2.1
Name: javautils
Version: 0.1.0
Summary: A python based CLI tool to simplify the time consuming, repetitive tasks of Java development.
Author-email: Atharv Kurdukar <3atharvkurdukar@gmail.com>
License: Copyright (c) 2012-2024 Scott Chacon and others
Classifier: License :: OSI Approved :: MIT License
Classifier: Operating System :: OS Independent
Classifier: Programming Language :: Python :: 3.8
Classifier: Programming Language :: Python :: 3.9
Classifier: Programming Language :: Python :: 3.10
Classifier: Topic :: Software Development :: Build Tools
Requires-Python: >=3.8
License-File: LICENSE
Requires-Dist: click >=8.1.7
Requires-Dist: PyInquirer >=1.0.3
Requires-Dist: stashy >=0.7
